neca/__init__.py
neca/__main__.py
neca/connectors.py
neca/events.py
neca/generators.py
neca/log.py
neca/session.py
neca/settings.py
neca/demos/apexcharts_example/main.py
neca/demos/apexcharts_example/templates/index.html
neca/demos/bar_chart_example/main.py
neca/demos/bar_chart_example/templates/index.html
neca/demos/connector_example/main.py
neca/demos/connector_example/templates/index.html
neca/demos/form_example/main.py
neca/demos/form_example/templates/index.html
neca/demos/line_chart_example/main.py
neca/demos/line_chart_example/templates/index.html
neca/demos/linear_chart_example/main.py
neca/demos/linear_chart_example/templates/index.html
neca/demos/map_example/main.py
neca/demos/map_example/templates/index.html
neca/demos/pie_chart_example/main.py
neca/demos/pie_chart_example/templates/index.html
neca/demos/stocks_example/aapl.json
neca/demos/stocks_example/main.py
neca/demos/stocks_example/templates/index.html
neca/demos/tweets_example/main.py
neca/demos/tweets_example/weer.txt
neca/demos/tweets_example/templates/index.html
neca/statics/lib/apex.js
neca/statics/lib/barchart.js
neca/statics/lib/chart.js
neca/statics/lib/core.js
neca/statics/lib/form.js
neca/statics/lib/linearchart.js
neca/statics/lib/linechart.js
neca/statics/lib/log.js
neca/statics/lib/map.js
neca/statics/lib/new_block.js
neca/statics/lib/piechart.js
neca/statics/lib/socket.io.js
neca/statics/lib/tweets.js
neca/statics/res/DefaultTwitterUser.png
neca/statics/style/tweet.css
neca/templates/basic/main.py
neca/templates/basic/templates/index.html
neca/tutorials/T1/README.md
neca/tutorials/T1/main.py
neca/tutorials/T1/templates/index.html
neca/tutorials/T2/README.md
neca/tutorials/T2/main.py
neca/tutorials/T2/templates/index.html
neca-2.1.13.dist-info/LICENSE
neca-2.1.13.dist-info/METADATA
neca-2.1.13.dist-info/WHEEL
neca-2.1.13.dist-info/entry_points.txt
neca-2.1.13.dist-info/top_level.txt
neca-2.1.13.dist-info/RECORD
