Metadata-Version: 2.1
Name: neca
Version: 2.1.13
Summary: ECA: Event Condition Action 
Home-page: https://github.com/NiekAukes/eca2
Author: Niek Aukes
Author-email: niek.aukes@gmail.com
Project-URL: Bug Reports, https://github.com/NiekAukes/eca2/issues
Project-URL: Source, https://github.com/NiekAukes/eca2
Classifier: Development Status :: 5 - Production/Stable
Classifier: Intended Audience :: Developers
Classifier: Topic :: Software Development :: Build Tools
Classifier: License :: OSI Approved :: MIT License
Classifier: Programming Language :: Python :: 3
Classifier: Programming Language :: Python :: 3.10
Classifier: Programming Language :: Python :: 3.11
Classifier: Programming Language :: Python :: 3.12
Classifier: Programming Language :: Python :: 3.13
Classifier: Programming Language :: Python :: 3 :: Only
Requires-Python: >=3.10, <4
License-File: LICENSE
Requires-Dist: flask
Requires-Dist: flask-socketio
Requires-Dist: flask-sock
Requires-Dist: InquirerPy
Requires-Dist: rich
Requires-Dist: typer
